{
  "name": "Simple Opentrons Transfer",
  "description": "Opentrons-only workflow: transfer liquid from one well to another",
  "version": "1.0.0",
  "author": "AC-OTFlex",
  "created": "2026-03-04",
  "workflow": {
    "nodes": [
      {
        "id": "start",
        "type": "input",
        "label": "Start",
        "params": {}
      },
      {
        "id": "transfer_1",
        "type": "otflexTransfer",
        "label": "Transfer Liquid",
        "params": {
          "from": {
            "labware": "source_plate",
            "well": "C2",
            "offsetX": 0,
            "offsetY": 0,
            "offsetZ": 5
          },
          "to": {
            "labware": "destination_plate",
            "well": "A1",
            "offsetX": 0,
            "offsetY": 0,
            "offsetZ": 20
          },
          "volume_uL": 50,
          "move_speed": 120,
          "pipette": "p50_single_flex",
          "tiprack": "tiprack_50ul"
        }
      },
      {
        "id": "end",
        "type": "output",
        "label": "End",
        "params": {}
      }
    ],
    "edges": [
      {
        "id": "e1",
        "source": "start",
        "target": "transfer_1",
        "type": "default"
      },
      {
        "id": "e2",
        "source": "transfer_1",
        "target": "end",
        "type": "default"
      }
    ]
  },
  "devices": {
    "otflex": {
      "module": "otflex_runtime.py",
      "controller_ip": "169.254.179.32",
      "arduino": {
        "port": "COM4",
        "baudrate": 115200
      },
      "deck": {
        "slots": {
          "B1": {
            "name": "destination_plate",
            "display": "destination",
            "labware": "actuated_reactor",
            "file": "data/labware_definitions/actuated_reactor.json",
            "slot_label": "B1"
          },
          "B2": {
            "name": "source_plate",
            "display": "source",
            "labware": "11_vials_20mL",
            "file": "data/labware_definitions/sdl1_11_vials_20mL.json",
            "slot_label": "B2"
          },
          "D2": {
            "name": "tiprack_50ul",
            "display": "tiprack_50ul",
            "labware": "opentrons_flex_96_tiprack_50ul",
            "slot_label": "D2"
          }
        },
        "pipettes": {
          "left": {
            "model": "p50_single_flex",
            "mount": "left"
          }
        }
      }
    }
  }
}
